NamasteiG/VerifyData.py
NamasteiG/__init__.py
NamasteiG/example.py
NamasteiG-0.3.14.dist-info/LICENSE
NamasteiG-0.3.14.dist-info/METADATA
NamasteiG-0.3.14.dist-info/WHEEL
NamasteiG-0.3.14.dist-info/top_level.txt
NamasteiG-0.3.14.dist-info/RECORD
