Metadata-Version: 2.1
Name: NamasteiG
Version: 0.3.14
Summary: Most PowerFull Instagram Library
Author-email: Abhinav Bhardwaj <abhinav.bhardwaj.56614@gmail.com>
Project-URL: Homepage, https://t.me/namastelibrary
Project-URL: Bug Tracker, https://t.me/namastehackers
Classifier: Programming Language :: Python :: 3
Classifier: License :: OSI Approved :: MIT License
Classifier: Operating System :: OS Independent
Requires-Python: >=3.9
License-File: LICENSE
